mealy_1101.v
module mealy_1101(clk,reset,x,y);
input clk,reset,x;
output reg  y;

parameter s0=2'b00;
parameter s1=2'b01;
parameter s2=2'b10;
parameter s3=2'b11;
	
reg [1:0] ps,ns;

always@(posedge clk or posedge reset) begin
	
	if(reset)
		ps<=s0;
	else
		ps<=ns;
		
end


always@(*) begin

case(ps)

s0:
begin
ns=x?s1:s0;
y=1'b0;
end

s1:
begin
ns=x?s2:s0;
y=1'b0;
end

s2:
begin
ns=x?s2:s3;
y=1'b0;
end

s3:
begin
ns=x?s1:s0;
y=x?1'b1:1'b0;
end
	
default:y=1'b0;

endcase

end

endmodule

mealy_1101_tb.v



module mealy_1101_tb();
reg clk;
reg reset;
reg x;
wire y;

mealy_1101 dut(.clk(clk),.reset(reset),.x(x),.y(y));

initial begin
clk=1'b0;
reset=1'b1;
x=1'b1;

#10
reset=1'b0;
x=1'b1;

#10
x=1'b0;

#10
x=1'b1;

#10
x=1'b0;

#10
x=1'b1;

#10
x=1'b1;

#10
x=1'b0;

#10
x=1'b1;

#10
x=1'b0;

#100 $finish;

end

always #5 clk=~clk;


initial 
begin
$dumpfile("seq_out.vcd");
$dumpvars;
end


endmodule

seq_out.vcd
$date
	Mon May 20 19:58:24 2024
$end
$version
	Icarus Verilog
$end
$timescale
	1s
$end
$scope module mealy_1101_tb $end
$var wire 1 ! y $end
$var reg 1 " clk $end
$var reg 1 # reset $end
$var reg 1 $ x $end
$scope module dut $end
$var wire 1 " clk $end
$var wire 1 # reset $end
$var wire 1 $ x $end
$var reg 2 % ns [1:0] $end
$var reg 2 & ps [1:0] $end
$var reg 1 ! y $end
$upscope $end
$upscope $end
$enddefinitions $end
#0
$dumpvars
b0 &
b1 %
1$
1#
0"
0!
$end
#5
1"
#10
0"
0#
#15
b10 %
b1 &
1"
#20
b0 %
0"
0$
#25
b0 &
1"
#30
b1 %
0"
1$
#35
b10 %
b1 &
1"
#40
b0 %
0"
0$
#45
b0 &
1"
#50
b1 %
0"
1$
#55
b10 %
b1 &
1"
#60
0"
#65
b10 &
1"
#70
b11 %
0"
0$
#75
b0 %
b11 &
1"
#80
1!
b1 %
0"
1$
#85
0!
b10 %
b1 &
1"
#90
b0 %
0"
0$
#95
b0 &
1"
